tracwikiextras
