Metadata-Version: 2.1
Name: TracWikiExtras
Version: 1.3.1
Summary: Plugin for Trac which extends the wiki with some extras
Home-page: https://trac-hacks.org/wiki/WikiExtrasPlugin
Author: Mikael Relbe
Author-email: mikael@relbe.se
License: BSD
Keywords: trac wiki plugin icons smileys entities symbols color phrases boxes
Platform: UNKNOWN
Classifier: Framework :: Trac
Requires-Dist: Trac
